pyrefra/Pyrefra.py
pyrefra/__init__.py
pyrefra/__main__.py
pyrefra/pyrefra_logo_old.png
pyrefra/pyrefra_script.py
pyrefra/pyrefra_start.py
pyrefra/refraData.py
pyrefra/version.py
pyrefra/data/data.py
pyrefra/data/files.py
pyrefra/data/geometry.py
pyrefra/data/traces.py
pyrefra/plotting/refraPlot.py
pyrefra/plotting/refraWindow.ui
pyrefra/utilities/utilities.py
pyrefra-25.8.1.dist-info/licenses/LICENSE.txt
pyrefra-25.8.1.dist-info/METADATA
pyrefra-25.8.1.dist-info/WHEEL
pyrefra-25.8.1.dist-info/entry_points.txt
pyrefra-25.8.1.dist-info/top_level.txt
pyrefra-25.8.1.dist-info/RECORD
