Metadata-Version: 2.4
Name: pyrefra
Version: 25.8.1
Summary: Data treatment for refraction seismic data
Author-email: Hermann ZEYEN <hermann.zeyen@universite-paris-saclay.fr>
Project-URL: Repository, https://github.com/HZeyen/PyRefra
Classifier: Development Status :: 3 - Alpha
Classifier: Intended Audience :: Science/Research
Classifier: Intended Audience :: Developers
Classifier: License :: OSI Approved :: BSD License
Classifier: Programming Language :: Python
Classifier: Programming Language :: Python :: 3
Classifier: Programming Language :: Python :: 3.10
Classifier: Programming Language :: Python :: 3.11
Classifier: Topic :: Software Development
Classifier: Topic :: Scientific/Engineering
Classifier: Typing :: Typed
Classifier: Operating System :: Microsoft :: Windows
Classifier: Operating System :: POSIX
Classifier: Operating System :: Unix
Classifier: Operating System :: MacOS
Requires-Python: >=3.09
License-File: LICENSE.txt
Requires-Dist: pygimli
Requires-Dist: scikit-learn
Requires-Dist: numpy
Requires-Dist: matplotlib>3.6
Requires-Dist: obspy
Requires-Dist: statsmodels
Requires-Dist: colorcet
Requires-Dist: PyQt5
Provides-Extra: gui
Requires-Dist: PyQt5; extra == "gui"
Dynamic: license-file
